bitcoinexchanges/__init__.py
bitcoinexchanges-0.1.dist-info/LICENSE.txt
bitcoinexchanges-0.1.dist-info/METADATA
bitcoinexchanges-0.1.dist-info/WHEEL
bitcoinexchanges-0.1.dist-info/top_level.txt
bitcoinexchanges-0.1.dist-info/RECORD
